{
  "domain": "autoboerkop.dk",
  "job_id": "scan-2026-04-05-eb1ab0a5",
  "status": "completed",
  "scan_result": {
    "domain": "autoboerkop.dk",
    "cms": "",
    "server": "",
    "hosting": "Cloudflare",
    "ssl_valid": true,
    "ssl_issuer": "Let's Encrypt",
    "ssl_expiry": "2026-06-17",
    "ssl_days_remaining": 72,
    "detected_plugins": [],
    "plugin_versions": {},
    "detected_themes": [],
    "headers": {
      "x_frame_options": false,
      "content_security_policy": false,
      "strict_transport_security": false,
      "x_content_type_options": true,
      "permissions_policy": false,
      "referrer_policy": false,
      "server_value": "",
      "x_powered_by": ""
    },
    "tech_stack": [
      "Bootstrap:4.3.1",
      "BootstrapCDN:4.3.1",
      "Cloudflare",
      "Google Analytics",
      "Microsoft ASP.NET",
      "Popper:1.14.7",
      "cdnjs",
      "jQuery CDN",
      "jQuery:3.3.1"
    ],
    "meta_author": "",
    "footer_credit": "",
    "raw_httpx": {
      "timestamp": "2026-04-05T14:51:42.17696026Z",
      "cdn_name": "aws",
      "cdn_type": "cloud",
      "port": "443",
      "url": "https://autoboerkop.dk",
      "input": "autoboerkop.dk",
      "title": "AutoCenter på Toppen | Bilværksted, automekaniker, bilmekaniker, bilværksted | 7080 Børkop",
      "scheme": "https",
      "content_type": "text/html",
      "method": "GET",
      "host": "autoboerkop.dk",
      "host_ip": "63.33.163.67",
      "path": "/",
      "final_url": "https://www.autoboerkop.dk/",
      "time": "988.343552ms",
      "chain_status_codes": [
        301,
        200
      ],
      "a": [
        "63.33.163.67"
      ],
      "tech": [
        "Bootstrap:4.3.1",
        "BootstrapCDN:4.3.1",
        "Cloudflare",
        "Google Analytics",
        "Microsoft ASP.NET",
        "Popper:1.14.7",
        "cdnjs",
        "jQuery CDN",
        "jQuery:3.3.1"
      ],
      "words": 2264,
      "lines": 1086,
      "status_code": 200,
      "content_length": 43392,
      "failed": false,
      "knowledgebase": {
        "pHash": 0
      },
      "resolvers": [
        "1.1.1.1:53",
        "1.0.0.1:53"
      ],
      "cpe": [
        {
          "product": "webp_server_go",
          "vendor": "webp",
          "cpe": "cpe:2.3:a:webp:webp_server_go:*:*:*:*:*:*:*:*"
        },
        {
          "product": "ektron_content_management_system",
          "vendor": "ektron",
          "cpe": "cpe:2.3:a:ektron:ektron_content_management_system:*:*:*:*:*:*:*:*"
        }
      ]
    },
    "subdomains": [],
    "dns_records": {
      "a": [
        "63.33.163.67"
      ],
      "aaaa": [],
      "cname": [],
      "mx": [
        "autoboerkop-dk.mail.protection.outlook.com"
      ],
      "ns": [
        "ns1.curanet.dk",
        "ns2.curanet.dk"
      ],
      "txt": [
        "facebook-domain-verification=umc0msfss7v7x9m65pgoexaawfguu7",
        "v=spf1 include:spf.protection.outlook.com -all"
      ]
    },
    "ct_certificates": [],
    "tls_version": "",
    "tls_cipher": "",
    "tls_bits": 0,
    "exposed_cloud_storage": []
  },
  "brief": {
    "domain": "autoboerkop.dk",
    "cvr": "prospect",
    "company_name": "autoboerkop.dk",
    "scan_date": "2026-04-05",
    "bucket": "E",
    "gdpr_sensitive": true,
    "gdpr_reasons": [
      "Visitor tracking: Google Analytics"
    ],
    "industry": "",
    "technology": {
      "cms": "",
      "hosting": "Cloudflare",
      "ssl": {
        "valid": true,
        "issuer": "Let's Encrypt",
        "expiry": "2026-06-17",
        "days_remaining": 72,
        "tls_version": ""
      },
      "server": "",
      "detected_plugins": [],
      "plugin_versions": {},
      "detected_themes": [],
      "headers": {
        "x_frame_options": false,
        "content_security_policy": false,
        "strict_transport_security": false,
        "x_content_type_options": true,
        "permissions_policy": false,
        "referrer_policy": false,
        "server_value": "",
        "x_powered_by": ""
      }
    },
    "tech_stack": [
      "Bootstrap:4.3.1",
      "BootstrapCDN:4.3.1",
      "Cloudflare",
      "Google Analytics",
      "Microsoft ASP.NET",
      "Popper:1.14.7",
      "cdnjs",
      "jQuery CDN",
      "jQuery:3.3.1"
    ],
    "plugin_versions": {},
    "subdomains": {
      "count": 0,
      "list": []
    },
    "dns": {
      "a": [
        "63.33.163.67"
      ],
      "aaaa": [],
      "cname": [],
      "mx": [
        "autoboerkop-dk.mail.protection.outlook.com"
      ],
      "ns": [
        "ns1.curanet.dk",
        "ns2.curanet.dk"
      ],
      "txt": [
        "facebook-domain-verification=umc0msfss7v7x9m65pgoexaawfguu7",
        "v=spf1 include:spf.protection.outlook.com -all"
      ]
    },
    "cloud_exposure": [],
    "agency": {
      "meta_author": "",
      "footer_credit": ""
    },
    "findings": [
      {
        "severity": "medium",
        "description": "Missing HSTS header (HTTP Strict Transport Security)",
        "risk": "Browsers are not instructed to always use HTTPS. On unsecured networks (public WiFi), a visitor's first connection could be intercepted before the redirect to HTTPS occurs."
      },
      {
        "severity": "low",
        "description": "Missing Content-Security-Policy header",
        "risk": "The browser has no restrictions on which scripts can run on the page. If the site is compromised, injected scripts can operate without constraint."
      },
      {
        "severity": "low",
        "description": "Missing X-Frame-Options header",
        "risk": "The website can be embedded in frames on other sites. This enables clickjacking attacks where users interact with hidden elements overlaid on the legitimate page."
      },
      {
        "severity": "low",
        "description": "Missing Permissions-Policy header",
        "risk": "The browser is not instructed to restrict access to device features (camera, microphone, geolocation). Third-party scripts embedded on the page could request these permissions."
      },
      {
        "severity": "low",
        "description": "Missing Referrer-Policy header",
        "risk": "The browser may send the full page URL to third-party sites when visitors click links. This can leak internal page paths or query parameters."
      }
    ]
  },
  "timing": {
    "robots_txt": 248,
    "ssl": 168,
    "headers": 593,
    "meta": 760,
    "httpx": 3096,
    "webanalyze": 4,
    "dnsx": 749,
    "total_ms": 5627
  },
  "cache_stats": {
    "hits": 3,
    "misses": 6
  }
}