{
  "domain": "nov.dk",
  "cvr": "prospect",
  "company_name": "nov.dk",
  "scan_date": "2026-04-05",
  "bucket": "E",
  "gdpr_sensitive": false,
  "gdpr_reasons": [],
  "industry": "",
  "technology": {
    "cms": "",
    "hosting": "Unknown",
    "ssl": {
      "valid": true,
      "issuer": "DigiCert Inc",
      "expiry": "2026-07-26",
      "days_remaining": 112,
      "tls_version": ""
    },
    "server": "",
    "detected_plugins": [],
    "plugin_versions": {},
    "detected_themes": [],
    "headers": {
      "x_frame_options": true,
      "content_security_policy": true,
      "strict_transport_security": true,
      "x_content_type_options": true,
      "permissions_policy": false,
      "referrer_policy": false,
      "server_value": "",
      "x_powered_by": "ASP.NET"
    }
  },
  "tech_stack": [
    "Azure",
    "Azure Front Door",
    "Bootstrap",
    "DNN",
    "HSTS",
    "Microsoft ASP.NET",
    "Modernizr",
    "Onsen UI",
    "bxSlider",
    "jQuery",
    "jQuery Migrate",
    "jQuery UI:01"
  ],
  "plugin_versions": {},
  "subdomains": {
    "count": 0,
    "list": []
  },
  "dns": {
    "a": [
      "20.107.224.17"
    ],
    "aaaa": [],
    "cname": [],
    "mx": [
      "nov-dk.mail.protection.outlook.com"
    ],
    "ns": [
      "ns1-01.azure-dns.com",
      "ns2-01.azure-dns.net",
      "ns3-01.azure-dns.org",
      "ns4-01.azure-dns.info"
    ],
    "txt": [
      "v=spf1 include:spf.protection.outlook.com -all",
      "MS=ms44657560"
    ]
  },
  "cloud_exposure": [
    {
      "bucket_name": "dimma.ams3.digitaloceanspaces.com",
      "file_count": 3
    },
    {
      "bucket_name": "borjes.s3.amazonaws.com",
      "file_count": 85
    },
    {
      "bucket_name": "gameassets.cinemataztic.com.storage.googleapis.com",
      "file_count": 8
    },
    {
      "bucket_name": "shfstor.blob.core.windows.net",
      "file_count": 1
    },
    {
      "bucket_name": "webcrawler.fra1.digitaloceanspaces.com",
      "file_count": 2
    },
    {
      "bucket_name": "astonmartin.blob.core.windows.net",
      "file_count": 1
    },
    {
      "bucket_name": "viewpointcloud.blob.core.windows.net",
      "file_count": 1
    },
    {
      "bucket_name": "sisel.s3.amazonaws.com",
      "file_count": 1
    }
  ],
  "agency": {
    "meta_author": "",
    "footer_credit": ""
  },
  "findings": [
    {
      "severity": "low",
      "description": "Missing Permissions-Policy header",
      "risk": "The browser is not instructed to restrict access to device features (camera, microphone, geolocation). Third-party scripts embedded on the page could request these permissions."
    },
    {
      "severity": "low",
      "description": "Missing Referrer-Policy header",
      "risk": "The browser may send the full page URL to third-party sites when visitors click links. This can leak internal page paths or query parameters."
    },
    {
      "severity": "info",
      "description": "X-Powered-By header discloses technology: ASP.NET",
      "risk": "The server advertises its backend technology in HTTP headers. This gives attackers specific version information to look up known vulnerabilities."
    },
    {
      "severity": "high",
      "description": "8 exposed cloud storage buckets detected",
      "risk": "Files stored in these buckets are publicly accessible to anyone on the internet. This may include internal documents, backups, or customer data."
    }
  ]
}